LICENSE
README.md
setup.py
ToPython.egg-info/PKG-INFO
ToPython.egg-info/SOURCES.txt
ToPython.egg-info/dependency_links.txt
ToPython.egg-info/requires.txt
ToPython.egg-info/top_level.txt
Topython/ToPython.py
Topython/__init__.py