Metadata-Version: 2.1
Name: ToPython
Version: 0.2
Summary: Best library to check Instagram applications
Home-page: https://t.me/Topython
Author: L7N Iraqi
Author-email: l7npypi@gmail.com
Classifier: Programming Language :: Python :: 3
Classifier: License :: OSI Approved :: MIT License
Classifier: Operating System :: OS Independent
Requires-Python: >=3.6
License-File: LICENSE
Requires-Dist: requests
